ncloud_autoscaling/__init__.py
ncloud_autoscaling/api_client.py
ncloud_autoscaling/configuration.py
ncloud_autoscaling/rest.py
ncloud_autoscaling/api/__init__.py
ncloud_autoscaling/api/v2_api.py
ncloud_autoscaling/model/__init__.py
ncloud_autoscaling/model/access_control_group.py
ncloud_autoscaling/model/activity_log.py
ncloud_autoscaling/model/adjustment_type.py
ncloud_autoscaling/model/auto_scaling_group.py
ncloud_autoscaling/model/common_code.py
ncloud_autoscaling/model/configuration_log.py
ncloud_autoscaling/model/create_auto_scaling_group_request.py
ncloud_autoscaling/model/create_auto_scaling_group_response.py
ncloud_autoscaling/model/create_launch_configuration_request.py
ncloud_autoscaling/model/create_launch_configuration_response.py
ncloud_autoscaling/model/delete_auto_scaling_group_request.py
ncloud_autoscaling/model/delete_auto_scaling_group_response.py
ncloud_autoscaling/model/delete_auto_scaling_launch_configuration_request.py
ncloud_autoscaling/model/delete_auto_scaling_launch_configuration_response.py
ncloud_autoscaling/model/delete_policy_request.py
ncloud_autoscaling/model/delete_policy_response.py
ncloud_autoscaling/model/delete_scheduled_action_request.py
ncloud_autoscaling/model/delete_scheduled_action_response.py
ncloud_autoscaling/model/execute_policy_request.py
ncloud_autoscaling/model/execute_policy_response.py
ncloud_autoscaling/model/get_adjustment_type_list_request.py
ncloud_autoscaling/model/get_adjustment_type_list_response.py
ncloud_autoscaling/model/get_auto_scaling_activity_log_list_request.py
ncloud_autoscaling/model/get_auto_scaling_activity_log_list_response.py
ncloud_autoscaling/model/get_auto_scaling_configuration_log_list_request.py
ncloud_autoscaling/model/get_auto_scaling_configuration_log_list_response.py
ncloud_autoscaling/model/get_auto_scaling_group_list_request.py
ncloud_autoscaling/model/get_auto_scaling_group_list_response.py
ncloud_autoscaling/model/get_auto_scaling_policy_list_request.py
ncloud_autoscaling-1.1.1.dist-info/LICENSE
ncloud_autoscaling-1.1.1.dist-info/METADATA
ncloud_autoscaling-1.1.1.dist-info/WHEEL
ncloud_autoscaling-1.1.1.dist-info/top_level.txt
ncloud_autoscaling-1.1.1.dist-info/RECORD
