Metadata-Version: 1.0
Name: ncloud-autoscaling
Version: 1.1.1
Summary: autoscaling
Home-page: UNKNOWN
Author: UNKNOWN
Author-email: UNKNOWN
License: UNKNOWN
Keywords: autoscaling
Platform: UNKNOWN
